qulacsvis/__init__.py
qulacsvis/models/__init__.py
qulacsvis/models/circuit.py
qulacsvis/qulacs/__init__.py
qulacsvis/qulacs/circuit.py
qulacsvis/utils/__init__.py
qulacsvis/utils/gate.py
qulacsvis/utils/latex.py
qulacsvis/visualization/__init__.py
qulacsvis/visualization/circuit_drawer.py
qulacsvis/visualization/circuit_parser.py
qulacsvis/visualization/latex.py
qulacsvis/visualization/matplotlib.py
qulacsvis/visualization/text.py
qulacsvis-0.7.5.dist-info/LICENSE
qulacsvis-0.7.5.dist-info/METADATA
qulacsvis-0.7.5.dist-info/WHEEL
qulacsvis-0.7.5.dist-info/RECORD
