Metadata-Version: 2.3
Name: qulacsvis
Version: 0.7.5
Summary: visualizers for qulacs
License: MIT
Author: Qulacs-Osaka
Author-email: you@example.com
Requires-Python: >=3.9
Classifier: License :: OSI Approved :: MIT License
Classifier: Programming Language :: Python :: 3
Classifier: Programming Language :: Python :: 3.9
Classifier: Programming Language :: Python :: 3.10
Classifier: Programming Language :: Python :: 3.11
Classifier: Programming Language :: Python :: 3.12
Classifier: Programming Language :: Python :: 3.13
Requires-Dist: Pillow (>=9.5.0,<10.0.0)
Requires-Dist: Qulacs (>=0.5.0)
Requires-Dist: dataclasses-json (>=0.5)
Requires-Dist: matplotlib (>=3.4.3,<4.0.0)
Requires-Dist: numpy (>=1.24.0)
Requires-Dist: temp (>=2020.7.2,<2021.0.0)
Project-URL: Documentation, https://qulacs-osaka.github.io/qulacs-visualizer
Project-URL: Homepage, https://github.com/Qulacs-Osaka/qulacs-visualizer
Project-URL: Repository, https://github.com/Qulacs-Osaka/qulacs-visualizer
